LICENSE
pwnedpasswords_offline/__init__.py
pwnedpasswords_offline/bloom.py
pwnedpasswords_offline/checker.py
pwnedpasswords_offline/helper.py
pwnedpasswords_offline/tools/__init__.py
pwnedpasswords_offline/tools/seed_bloom.py
pwnedpasswords_offline/tools/speed.py
pwnedpasswords_offline-1.2.0.dist-info/entry_points.txt
pwnedpasswords_offline-1.2.0.dist-info/LICENSE
pwnedpasswords_offline-1.2.0.dist-info/WHEEL
pwnedpasswords_offline-1.2.0.dist-info/METADATA
pwnedpasswords_offline-1.2.0.dist-info/RECORD
