Metadata-Version: 2.1
Name: pwnedpasswords-offline
Version: 1.2.0
Summary: Pwned Passwords check (offline)
Home-page: https://github.com/henryk/pwnedpasswords-offline
License: LGPL-2.1-or-later
Author: Henryk Plötz
Author-email: henryk@ploetzli.ch
Requires-Python: >=3.6.2,<4.0.0
Classifier: License :: OSI Approved
Classifier: Programming Language :: Python :: 3
Classifier: Programming Language :: Python :: 3.10
Classifier: Programming Language :: Python :: 3.7
Classifier: Programming Language :: Python :: 3.8
Classifier: Programming Language :: Python :: 3.9
Project-URL: Repository, https://github.com/henryk/pwnedpasswords-offline
